firepup650/__init__.py
firepup650/__init__.pyi
firepup650/py.typed
firepup650-1.1.0.dist-info/LICENSE
firepup650-1.1.0.dist-info/METADATA
firepup650-1.1.0.dist-info/WHEEL
firepup650-1.1.0.dist-info/RECORD
