Metadata-Version: 2.3
Name: firepup650
Version: 1.1.0
Summary: Package containing various shorthand things I use, and a few imports I almost always use
License: MIT
Author: Firepup650
Author-email: firepup650@firepup650.com
Requires-Python: >=3.8,<4.0
Classifier: Development Status :: 5 - Production/Stable
Classifier: Environment :: Console
Classifier: Intended Audience :: Developers
Classifier: License :: OSI Approved :: MIT License
Classifier: Natural Language :: English
Classifier: Operating System :: OS Independent
Classifier: Programming Language :: Python :: 3
Classifier: Programming Language :: Python :: 3.8
Classifier: Programming Language :: Python :: 3.9
Classifier: Programming Language :: Python :: 3.10
Classifier: Programming Language :: Python :: 3.11
Classifier: Programming Language :: Python :: 3.12
Classifier: Programming Language :: Python :: 3.13
Requires-Dist: fkeycapture (>=1.3.0,<2.0.0)
Requires-Dist: fpsql (>=1,<2,!=1.0.26)
Project-URL: Bug Tracker, https://git.h.hackclub.app/Firepup650/firepup-py-package/issues
Project-URL: Repository, https://git.h.hackclub.app/Firepup650/firepup-py-package
